mcp_server.py
cellrepair_mcp_server-1.0.2.dist-info/METADATA
cellrepair_mcp_server-1.0.2.dist-info/WHEEL
cellrepair_mcp_server-1.0.2.dist-info/entry_points.txt
cellrepair_mcp_server-1.0.2.dist-info/top_level.txt
cellrepair_mcp_server-1.0.2.dist-info/RECORD
