Metadata-Version: 2.1
Name: cellrepair-mcp-server
Version: 1.0.2
Summary: Claude MCP Server for CellRepair.AI - Access 4882 autonomous agents from Claude
Home-page: https://github.com/PowerForYou74/cellrepair-mcp-server
Author: CellRepair Systems
Author-email: CellRepair Systems <ai@cellrepair.ai>
License: MIT
Project-URL: Homepage, https://cellrepair.ai
Project-URL: Documentation, https://cellrepair.ai/api/
Project-URL: Repository, https://github.com/cellrepair-systems/cellrepair-ai
Project-URL: Bug Reports, https://github.com/cellrepair-systems/cellrepair-ai/issues
Project-URL: Get API Key, https://cellrepair.ai/api/?utm_source=claude&utm_medium=mcp
Keywords: claude,mcp,model-context-protocol,ai,agents,multi-agent,anthropic,artificial-intelligence
Classifier: Development Status :: 5 - Production/Stable
Classifier: Intended Audience :: Developers
Classifier: Topic :: Software Development :: Libraries :: Python Modules
Classifier: Topic :: Scientific/Engineering :: Artificial Intelligence
Classifier: License :: OSI Approved :: MIT License
Classifier: Programming Language :: Python :: 3
Classifier: Programming Language :: Python :: 3.10
Classifier: Programming Language :: Python :: 3.11
Classifier: Programming Language :: Python :: 3.12
Requires-Python: >=3.10
Requires-Dist: mcp >=0.1.0
Requires-Dist: pydantic >=2.0.0
Requires-Dist: requests >=2.25.0
